pyzway-0.1.0.dist-info/DESCRIPTION.rst
pyzway-0.1.0.dist-info/METADATA
pyzway-0.1.0.dist-info/RECORD
pyzway-0.1.0.dist-info/WHEEL
pyzway-0.1.0.dist-info/metadata.json
pyzway-0.1.0.dist-info/top_level.txt
zway/__init__.py
zway/controller.py
zway/devices.py
zway/session.py
