Metadata-Version: 2.0
Name: pyzway
Version: 0.1.0
Summary: Python for Z-Way
Home-page: https://github.com/jschlyter/pyzway
Author: Jakob Schlyter
Author-email: jakob@kirei.se
License: UNKNOWN
Platform: UNKNOWN
Classifier: License :: OSI Approved :: BSD License
Classifier: Programming Language :: Python :: 3 :: Only
Requires-Dist: requests
Requires-Dist: setuptools
